llshash/__init__.py
llshash/llshash.py
llshash_package-0.1.0.dist-info/LICENSE
llshash_package-0.1.0.dist-info/METADATA
llshash_package-0.1.0.dist-info/WHEEL
llshash_package-0.1.0.dist-info/top_level.txt
llshash_package-0.1.0.dist-info/RECORD
