Metadata-Version: 2.1
Name: llshash-package
Version: 0.1.0
Summary: A locality sensitive hashing implementationoptimized for large data processing.
Home-page: https://github.com/m229abd/llshash
Author: Mostafa Abdolmaleki
Author-email: m229abd@gmail.com
Classifier: Programming Language :: Python :: 3
Classifier: License :: OSI Approved :: MIT License
Classifier: Operating System :: OS Independent
Requires-Python: >=3.7
License-File: LICENSE
Requires-Dist: numpy>=1.18.0
Requires-Dist: ray>=1.0.0
Provides-Extra: dev
Requires-Dist: pytest; extra == "dev"
Requires-Dist: black; extra == "dev"
Requires-Dist: twine; extra == "dev"
Requires-Dist: wheel; extra == "dev"
